README.txt
setup.py
OplogReplay.egg-info/PKG-INFO
OplogReplay.egg-info/SOURCES.txt
OplogReplay.egg-info/dependency_links.txt
OplogReplay.egg-info/requires.txt
OplogReplay.egg-info/top_level.txt
bin/oplogreplay
oplogreplay/__init__.py
oplogreplay/oplogreplayer.py
oplogreplay/oplogwatcher.py
oplogreplay/test/__init__.py
oplogreplay/test/test_oplogreplayer.py