Metadata-Version: 1.0
Name: OplogReplay
Version: 0.1.0
Summary: MongoDB oplog replay utility.
Home-page: http://pypi.python.org/pypi/OplogReplay/
Author: Mihnea Giurgea
Author-email: GiurgeaMihnea@gmail.com
License: LICENSE.txt
Platform: UNKNOWN
